sqless/__init__.py
sqless/client.py
sqless/database.py
sqless/server.py
sqless/sqless_config.py
sqless-0.2.2.dist-info/licenses/LICENSE
sqless-0.2.2.dist-info/METADATA
sqless-0.2.2.dist-info/WHEEL
sqless-0.2.2.dist-info/entry_points.txt
sqless-0.2.2.dist-info/top_level.txt
sqless-0.2.2.dist-info/RECORD
