Metadata-Version: 2.4
Name: sqless
Version: 0.2.2
Summary: An async HTTP server for SQLite, FileStorage and WebPage.
Home-page: https://github.com/pro1515151515/sqless
Author: pro1515151515
Author-email: pro1515151515@qq.com
Classifier: Development Status :: 3 - Alpha
Classifier: Intended Audience :: Developers
Classifier: License :: OSI Approved :: MIT License
Classifier: Operating System :: OS Independent
Classifier: Programming Language :: Python :: 3
Requires-Python: >=3.7
License-File: LICENSE
Requires-Dist: aiohttp>=3.8.0
Requires-Dist: orjson>=3.6.0
Requires-Dist: aiofiles>=0.8.0
Dynamic: author
Dynamic: author-email
Dynamic: classifier
Dynamic: description
Dynamic: description-content-type
Dynamic: home-page
Dynamic: license-file
Dynamic: requires-dist
Dynamic: requires-python
Dynamic: summary
